sumedha_matrix/__init__.py
sumedha_matrix/matrix.py
sumedha_matrix-1.0.0.dist-info/METADATA
sumedha_matrix-1.0.0.dist-info/WHEEL
sumedha_matrix-1.0.0.dist-info/licenses/LICENCE.txt
sumedha_matrix-1.0.0.dist-info/RECORD
